{
  "$schema": "https://json-schema.org/draft/2020-12/schema",
  "title": "Configuration for HkagTools",
  "$ref": "#/definitions/root",
  "definitions": {
    "root": {
      "type": "object",
      "properties": {
        "hkag_tools": {
          "$ref": "#/definitions/hkag_tools"
        }
      },
      "additionalProperties": false
    },
    "hkag_tools": {
      "type": "object",
      "properties": {
        "file_checker": {
          "title": "File checker allow-list",
          "type": "array",
          "items": {
            "type": "string"
          }
        },
        "system_config": {
          "type": "object",
          "additionalProperties": true
        }
      },
      "additionalProperties": false
    }
  }
}
